INDICovid19/INDICovid19.py
INDICovid19/__init__.py
INDICovid19-0.0.3.dist-info/LICENSE.txt
INDICovid19-0.0.3.dist-info/METADATA
INDICovid19-0.0.3.dist-info/WHEEL
INDICovid19-0.0.3.dist-info/top_level.txt
INDICovid19-0.0.3.dist-info/RECORD
