Metadata-Version: 2.1
Name: INDICovid19
Version: 0.0.3
Summary: Python Lib for api call on Indian Covid 19 dataset near real time
Home-page: https://github.com/deepstartup/INDICovid19
Author: Arghadeep Chaudhury
Author-email: arghadeep.chaudhury@gmail.com
License: UNKNOWN
Platform: UNKNOWN
Classifier: Programming Language :: Python :: 3
Classifier: License :: OSI Approved :: MIT License
Classifier: Operating System :: OS Independent
Requires-Dist: pandas
Requires-Dist: json2xml
Requires-Dist: requests
